{
  "trackers": [
    {
      "type": "cloudflare",
      "url": "https://static.cloudflareinsights.com/beacon.min.js/v8c78df7c7c0f484497ecbca7046644da1771523124516",
      "details": {
        "id": "cloudflare",
        "message": "Host files locally"
      }
    },
    {
      "type": "cloudflare",
      "url": "https://challenges.cloudflare.com/turnstile/v0/b/625261456364/api.js?onload=OBvX9&render=explicit",
      "details": {
        "id": "cloudflare",
        "message": "Host files locally"
      }
    },
    {
      "type": "cloudflare",
      "url": "https://challenges.cloudflare.com/cdn-cgi/challenge-platform/h/b/turnstile/f/ov2/av0/rch/5y729/0x4AAAAAAADnPIDROrmt1Wwj/light/fbE/new/normal?lang=auto",
      "details": {
        "id": "cloudflare",
        "message": "Host files locally"
      }
    },
    {
      "type": "cloudflare",
      "url": "https://challenges.cloudflare.com/cdn-cgi/challenge-platform/h/b/cmg/1",
      "details": {
        "id": "cloudflare",
        "message": "Host files locally"
      }
    },
    {
      "type": "cloudflare",
      "url": "https://challenges.cloudflare.com/cdn-cgi/challenge-platform/h/b/flow/ov1/529034901:1775358963:6wCDv293kunnYmTko3Rdv7ADe5oo1jbJJwFzrACG65Y/9e75740cef1bfb2c/m5CqS89xCK4Th3fBySXhZlkuBAQMzeMHpE5106qo4bY-1775359607-1.2.1.1-puRvILKYMU6VgsH_vhEx5eAMa7M.B_DYW33Mjbc_VDQ6eYKxz5xEsxoA4HcnEUNu",
      "details": {
        "id": "cloudflare",
        "message": "Host files locally"
      }
    },
    {
      "type": "cloudflare",
      "url": "https://challenges.cloudflare.com/cdn-cgi/challenge-platform/h/b/pat/9e75740cef1bfb2c/1775359608070/2bbc6f0460cad32be1e8b80c0efe79512999794020fe62f953ea479a7027c9b3/A4xbx5sfiK5F480",
      "details": {
        "id": "cloudflare",
        "message": "Host files locally"
      }
    },
    {
      "type": "cloudflare",
      "url": "https://challenges.cloudflare.com/cdn-cgi/challenge-platform/h/b/d/9e75740cef1bfb2c/1775359608073/mGEZB0pbFc9yKrI",
      "details": {
        "id": "cloudflare",
        "message": "Host files locally"
      }
    },
    {
      "type": "cloudflare",
      "url": "https://challenges.cloudflare.com/cdn-cgi/challenge-platform/h/b/flow/ov1/529034901:1775358963:6wCDv293kunnYmTko3Rdv7ADe5oo1jbJJwFzrACG65Y/9e75740cef1bfb2c/m5CqS89xCK4Th3fBySXhZlkuBAQMzeMHpE5106qo4bY-1775359607-1.2.1.1-puRvILKYMU6VgsH_vhEx5eAMa7M.B_DYW33Mjbc_VDQ6eYKxz5xEsxoA4HcnEUNu",
      "details": {
        "id": "cloudflare",
        "message": "Host files locally"
      }
    }
  ],
  "cookies": [
    {
      "name": "__cf_bm",
      "value": "l_Nc5fRJqsgHYIxG28tv.ulimG5EQLGeY.wfaGq8kfU-1775359607.3362014-1.0.1.1-vdVfvAwZhcpGp7G.Zg6SnM.jxi9xQTVa..ZoAx8jJlKmiCNZDKkyCUWbLpFXylj9vcJxNOO7dyxmXGSJGHF3pOHenPo0Ld44eLhKN_xLsn3B8UoVvqnpkpUhvQXm8kK1",
      "domain": ".economie.gouv.fr",
      "path": "/",
      "expires": 1775361407.421189,
      "size": 206,
      "httpOnly": true,
      "secure": true,
      "session": false,
      "priority": "Medium",
      "sourceScheme": "Secure",
      "sameParty": false
    }
  ],
  "headers": {
    "accept-ch": "Sec-CH-UA-Bitness, Sec-CH-UA-Arch, Sec-CH-UA-Full-Version, Sec-CH-UA-Mobile, Sec-CH-UA-Model, Sec-CH-UA-Platform-Version, Sec-CH-UA-Full-Version-List, Sec-CH-UA-Platform, Sec-CH-UA, UA-Bitness, UA-Arch, UA-Full-Version, UA-Mobile, UA-Model, UA-Platform-Version, UA-Platform, UA",
    "alt-svc": "h3=\":443\"; ma=86400",
    "cf-mitigated": "challenge",
    "cf-ray": "9e757408aed26fc4-CDG",
    "content-encoding": "br",
    "content-type": "text/html; charset=UTF-8",
    "critical-ch": "Sec-CH-UA-Bitness, Sec-CH-UA-Arch, Sec-CH-UA-Full-Version, Sec-CH-UA-Mobile, Sec-CH-UA-Model, Sec-CH-UA-Platform-Version, Sec-CH-UA-Full-Version-List, Sec-CH-UA-Platform, Sec-CH-UA, UA-Bitness, UA-Arch, UA-Full-Version, UA-Mobile, UA-Model, UA-Platform-Version, UA-Platform, UA",
    "cross-origin-embedder-policy": "require-corp",
    "cross-origin-opener-policy": "same-origin",
    "cross-origin-resource-policy": "same-origin",
    "date": "Sun, 05 Apr 2026 03:26:47 GMT",
    "origin-agent-cluster": "?1",
    "permissions-policy": "accelerometer=(),browsing-topics=(),camera=(),clipboard-read=(),clipboard-write=(),geolocation=(),gyroscope=(),hid=(),interest-cohort=(),magnetometer=(),microphone=(),payment=(),publickey-credentials-get=(),screen-wake-lock=(),serial=(),sync-xhr=(),usb=()",
    "referrer-policy": "same-origin",
    "server": "cloudflare",
    "server-timing": "chlray;desc=\"9e757408aed26fc4\"\ncfEdge;dur=1,cfOrigin;dur=0",
    "strict-transport-security": "max-age=15552000; includeSubDomains; preload",
    "vary": "accept-encoding",
    "x-content-type-options": "nosniff",
    "x-frame-options": "SAMEORIGIN"
  },
  "endpoints": [
    {
      "hostname": "www.economie.gouv.fr",
      "ip": "141.101.90.96",
      "geoip": {
        "registered_country": {
          "geoname_id": 6252001,
          "iso_code": "US",
          "names": {
            "de": "USA",
            "en": "United States",
            "es": "Estados Unidos",
            "fr": "États-Unis",
            "ja": "アメリカ",
            "pt-BR": "EUA",
            "ru": "США",
            "zh-CN": "美国"
          }
        }
      }
    },
    {
      "hostname": "static.cloudflareinsights.com",
      "ip": "104.16.80.73",
      "geoip": {
        "registered_country": {
          "geoname_id": 6252001,
          "iso_code": "US",
          "names": {
            "de": "USA",
            "en": "United States",
            "es": "Estados Unidos",
            "fr": "États-Unis",
            "ja": "アメリカ",
            "pt-BR": "EUA",
            "ru": "США",
            "zh-CN": "美国"
          }
        }
      }
    },
    {
      "hostname": "challenges.cloudflare.com",
      "ip": "104.18.95.41",
      "geoip": {
        "registered_country": {
          "geoname_id": 6252001,
          "iso_code": "US",
          "names": {
            "de": "USA",
            "en": "United States",
            "es": "Estados Unidos",
            "fr": "États-Unis",
            "ja": "アメリカ",
            "pt-BR": "EUA",
            "ru": "США",
            "zh-CN": "美国"
          }
        }
      }
    }
  ]
}
